redis_async_client/__init__.py
redis_async_client/core/__init__.py
redis_async_client/core/_base.py
redis_async_client/core/_constants.py
redis_async_client/core/_logger.py
redis_async_client/core/_types.py
redis_async_client/core/async_client.py
redis_async_client/core/exc.py
redis_async_client/core/settings.py
redis_async_client-0.1.7.dist-info/LICENSE
redis_async_client-0.1.7.dist-info/METADATA
redis_async_client-0.1.7.dist-info/WHEEL
redis_async_client-0.1.7.dist-info/RECORD
