Metadata-Version: 2.1
Name: redis-async-client
Version: 0.1.7
Summary: Redis async client.
Home-page: https://pypi.org/project/redis-async-client/
License: MIT
Author: deskent
Author-email: battenetciz@gmail.com
Requires-Python: >=3.10,<4.0
Classifier: License :: OSI Approved :: MIT License
Classifier: Programming Language :: Python :: 3
Classifier: Programming Language :: Python :: 3.10
Classifier: Programming Language :: Python :: 3.11
Classifier: Programming Language :: Python :: 3.12
Requires-Dist: redis (>=5.0.3,<6.0.0)
Project-URL: Repository, https://github.com/Deskent/redis_async_client
